LICENSE
README.md
setup.py
tcell_hooks/__init__.py
tcell_hooks/v1.py
tcell_hooks/version.py
tcell_hooks.egg-info/PKG-INFO
tcell_hooks.egg-info/SOURCES.txt
tcell_hooks.egg-info/dependency_links.txt
tcell_hooks.egg-info/top_level.txt