Metadata-Version: 2.1
Name: tcell-hooks
Version: 1.1.0
Summary: Allows custom event sending of login failures/success to TCell
Home-page: https://www.rapid7.com/products/tcell/
Author: Rapid7
License: No License
Platform: UNKNOWN
License-File: LICENSE
